{
    "cuartos": {
        "id": "45cb9ee5-278c-43cf-859c-6283f742bb38",
        "partidos": [
            {
                "local": "CR El Salvador Fem.",
                "resultadoA": "23",
                "resultadoB": "25",
                "visitante": "AVRFCB",
                "fecha": "05.05",
                "hora": ""
            },
            {
                "local": "CR Sant Cugat",
                "resultadoA": "26",
                "resultadoB": "17",
                "visitante": "U.Sevilla C.R.",
                "fecha": "05.05",
                "hora": ""
            },
            {
                "local": "",
                "resultadoA": "",
                "resultadoB": "",
                "visitante": "",
                "fecha": "",
                "hora": ""
            },
            {
                "local": "",
                "resultadoA": "",
                "resultadoB": "",
                "visitante": "",
                "fecha": "",
                "hora": ""
            }
        ]
    },
    "semifinales": {
        "id": "3fb99a65-fa79-44e1-86a3-d73b8bf4272a",
        "partidos": [
            {
                "local": "CR Majadahonda",
                "resultadoA": "27",
                "resultadoB": "17",
                "visitante": "CR Sant Cugat",
                "fecha": "11.05",
                "hora": ""
            },
            {
                "local": "CRAT",
                "resultadoA": "24",
                "resultadoB": "15",
                "visitante": "AVRFCB",
                "fecha": "12.05",
                "hora": ""
            }
        ]
    },
    "final": {
        "id": "2630099c-893f-4f6a-aabc-ddb9dac90cf3",
        "partidos": [
            {
                "local": "CR Majadahonda",
                "resultadoA": "13",
                "resultadoB": "12",
                "visitante": "CRAT",
                "fecha": "19.05",
                "hora": ""
            }
        ]
    }
}