[{"id": "8488424f-655d-4fc4-883c-f6f842fd80a0", "nombre": "Jornada 1", "partidos": [{"local": "Amorebieta", "resultadoA": "1", "resultadoB": "1", "visitante": "Levante"}, {"local": "Real Valladolid", "resultadoA": "2", "resultadoB": "0", "visitante": "Sporting"}, {"local": "Racing", "resultadoA": "4", "resultadoB": "0", "visitante": "Eibar"}, {"local": "Zaragoza", "resultadoA": "2", "resultadoB": "0", "visitante": "Villarreal B"}, {"local": "Elche", "resultadoA": "0", "resultadoB": "1", "visitante": "Racing Ferrol"}, {"local": "Burgos", "resultadoA": "1", "resultadoB": "1", "visitante": "Huesca"}, {"local": "Albacete", "resultadoA": "1", "resultadoB": "1", "visitante": "Espanyol"}, {"local": "Cartagena", "resultadoA": "0", "resultadoB": "1", "visitante": "Eldense"}, {"local": "Legan\u00e9s", "resultadoA": "0", "resultadoB": "1", "visitante": "Andorra"}, {"local": "Mirand\u00e9s", "resultadoA": "4", "resultadoB": "0", "visitante": "Alcorc\u00f3n"}, {"local": "Tenerife", "resultadoA": "1", "resultadoB": "0", "visitante": "Oviedo"}]}, {"id": "86527028-8876-4fba-8051-242470ed18aa", "nombre": "Jornada 2", "partidos": [{"local": "Andorra", "resultadoA": "3", "resultadoB": "2", "visitante": "Cartagena"}, {"local": "Zaragoza", "resultadoA": "1", "resultadoB": "0", "visitante": "Real Valladolid"}, {"local": "Eibar", "resultadoA": "2", "resultadoB": "1", "visitante": "Elche"}, {"local": "Espanyol", "resultadoA": "2", "resultadoB": "0", "visitante": "Racing"}, {"local": "Levante", "resultadoA": "3", "resultadoB": "2", "visitante": "Burgos"}, {"local": "Alcorc\u00f3n", "resultadoA": "0", "resultadoB": "2", "visitante": "Legan\u00e9s"}, {"local": "Oviedo", "resultadoA": "1", "resultadoB": "1", "visitante": "Racing Ferrol"}, {"local": "Sporting", "resultadoA": "3", "resultadoB": "0", "visitante": "Mirand\u00e9s"}, {"local": "Albacete", "resultadoA": "2", "resultadoB": "2", "visitante": "Amorebieta"}, {"local": "Villarreal B", "resultadoA": "3", "resultadoB": "1", "visitante": "Eldense"}, {"local": "Huesca", "resultadoA": "0", "resultadoB": "2", "visitante": "Tenerife"}]}, {"id": "d9ee9f70-b989-417a-8200-63ff55deeac9", "nombre": "Jornada 3", "partidos": [{"local": "Cartagena", "resultadoA": "0", "resultadoB": "1", "visitante": "Levante"}, {"local": "Burgos", "resultadoA": "1", "resultadoB": "0", "visitante": "Oviedo"}, {"local": "Tenerife", "resultadoA": "0", "resultadoB": "1", "visitante": "Zaragoza"}, {"local": "Elche", "resultadoA": "1", "resultadoB": "0", "visitante": "Villarreal B"}, {"local": "Real Valladolid", "resultadoA": "0", "resultadoB": "2", "visitante": "Alcorc\u00f3n"}, {"local": "Racing Ferrol", "resultadoA": "2", "resultadoB": "0", "visitante": "Sporting"}, {"local": "Amorebieta", "resultadoA": "3", "resultadoB": "0", "visitante": "Andorra"}, {"local": "Mirand\u00e9s", "resultadoA": "0", "resultadoB": "1", "visitante": "Espanyol"}, {"local": "Legan\u00e9s", "resultadoA": "2", "resultadoB": "0", "visitante": "Albacete"}, {"local": "Eldense", "resultadoA": "2", "resultadoB": "1", "visitante": "Eibar"}, {"local": "Racing", "resultadoA": "0", "resultadoB": "0", "visitante": "Huesca"}]}, {"id": "0529bf01-f4ee-4780-af16-8962d2dbc056", "nombre": "Jornada 4", "partidos": [{"local": "Alcorc\u00f3n", "resultadoA": "1", "resultadoB": "1", "visitante": "Racing Ferrol"}, {"local": "Albacete", "resultadoA": "2", "resultadoB": "0", "visitante": "Real Valladolid"}, {"local": "Sporting", "resultadoA": "2", "resultadoB": "1", "visitante": "Burgos"}, {"local": "Levante", "resultadoA": "1", "resultadoB": "1", "visitante": "Oviedo"}, {"local": "Elche", "resultadoA": "1", "resultadoB": "1", "visitante": "Racing"}, {"local": "Villarreal B", "resultadoA": "1", "resultadoB": "2", "visitante": "Cartagena"}, {"local": "Andorra", "resultadoA": "0", "resultadoB": "1", "visitante": "Tenerife"}, {"local": "Eibar", "resultadoA": "0", "resultadoB": "1", "visitante": "Legan\u00e9s"}, {"local": "Espanyol", "resultadoA": "3", "resultadoB": "2", "visitante": "Amorebieta"}, {"local": "Zaragoza", "resultadoA": "2", "resultadoB": "0", "visitante": "Eldense"}, {"local": "Huesca", "resultadoA": "1", "resultadoB": "1", "visitante": "Mirand\u00e9s"}]}, {"id": "3eac7465-5adf-4dad-85fd-e4ee1ecaa743", "nombre": "Jornada 5", "partidos": [{"local": "Levante", "resultadoA": "1", "resultadoB": "4", "visitante": "Espanyol"}, {"local": "Burgos", "resultadoA": "1", "resultadoB": "0", "visitante": "Eibar"}, {"local": "Oviedo", "resultadoA": "0", "resultadoB": "0", "visitante": "Sporting"}, {"local": "Legan\u00e9s", "resultadoA": "2", "resultadoB": "0", "visitante": "Huesca"}, {"local": "Tenerife", "resultadoA": "2", "resultadoB": "0", "visitante": "Albacete"}, {"local": "Racing Ferrol", "resultadoA": "2", "resultadoB": "2", "visitante": "Villarreal B"}, {"local": "Racing", "resultadoA": "1", "resultadoB": "0", "visitante": "Amorebieta"}, {"local": "Cartagena", "resultadoA": "1", "resultadoB": "3", "visitante": "Zaragoza"}, {"local": "Mirand\u00e9s", "resultadoA": "4", "resultadoB": "3", "visitante": "Andorra"}, {"local": "Real Valladolid", "resultadoA": "1", "resultadoB": "1", "visitante": "Elche"}, {"local": "Eldense", "resultadoA": "2", "resultadoB": "2", "visitante": "Alcorc\u00f3n"}]}, {"id": "42b8e259-1aec-4c2b-a6d5-2fc0fcca8461", "nombre": "Jornada 6", "partidos": [{"local": "Zaragoza", "resultadoA": "1", "resultadoB": "1", "visitante": "Racing"}, {"local": "Huesca", "resultadoA": "2", "resultadoB": "2", "visitante": "Villarreal B"}, {"local": "Alcorc\u00f3n", "resultadoA": "0", "resultadoB": "2", "visitante": "Levante"}, {"local": "Real Valladolid", "resultadoA": "1", "resultadoB": "0", "visitante": "Cartagena"}, {"local": "Albacete", "resultadoA": "2", "resultadoB": "1", "visitante": "Burgos"}, {"local": "Amorebieta", "resultadoA": "2", "resultadoB": "0", "visitante": "Mirand\u00e9s"}, {"local": "Eibar", "resultadoA": "2", "resultadoB": "0", "visitante": "Racing Ferrol"}, {"local": "Elche", "resultadoA": "1", "resultadoB": "0", "visitante": "Legan\u00e9s"}, {"local": "Espanyol", "resultadoA": "3", "resultadoB": "3", "visitante": "Eldense"}, {"local": "Sporting", "resultadoA": "2", "resultadoB": "1", "visitante": "Tenerife"}, {"local": "Andorra", "resultadoA": "1", "resultadoB": "0", "visitante": "Oviedo"}]}, {"id": "a0195a5e-ea64-42c0-8d3b-f11043c728d9", "nombre": "Jornada 7", "partidos": [{"local": "Cartagena", "resultadoA": "1", "resultadoB": "2", "visitante": "Eibar"}, {"local": "Andorra", "resultadoA": "0", "resultadoB": "0", "visitante": "Sporting"}, {"local": "Levante", "resultadoA": "2", "resultadoB": "0", "visitante": "Eldense"}, {"local": "Burgos", "resultadoA": "4", "resultadoB": "0", "visitante": "Elche"}, {"local": "Alcorc\u00f3n", "resultadoA": "0", "resultadoB": "2", "visitante": "Huesca"}, {"local": "Racing", "resultadoA": "2", "resultadoB": "1", "visitante": "Albacete"}, {"local": "Villarreal B", "resultadoA": "3", "resultadoB": "1", "visitante": "Amorebieta"}, {"local": "Oviedo", "resultadoA": "0", "resultadoB": "1", "visitante": "Real Valladolid"}, {"local": "Mirand\u00e9s", "resultadoA": "1", "resultadoB": "3", "visitante": "Legan\u00e9s"}, {"local": "Racing Ferrol", "resultadoA": "1", "resultadoB": "0", "visitante": "Zaragoza"}, {"local": "Tenerife", "resultadoA": "1", "resultadoB": "0", "visitante": "Espanyol"}]}, {"id": "02cd07e5-db7d-4a6c-8f62-faf90b8afb24", "nombre": "Jornada 8", "partidos": [{"local": "Legan\u00e9s", "resultadoA": "2", "resultadoB": "1", "visitante": "Racing"}, {"local": "Eibar", "resultadoA": "3", "resultadoB": "0", "visitante": "Tenerife"}, {"local": "Elche", "resultadoA": "0", "resultadoB": "0", "visitante": "Levante"}, {"local": "Albacete", "resultadoA": "3", "resultadoB": "1", "visitante": "Andorra"}, {"local": "Villarreal B", "resultadoA": "2", "resultadoB": "2", "visitante": "Alcorc\u00f3n"}, {"local": "Eldense", "resultadoA": "1", "resultadoB": "3", "visitante": "Oviedo"}, {"local": "Amorebieta", "resultadoA": "0", "resultadoB": "0", "visitante": "Cartagena"}, {"local": "Real Valladolid", "resultadoA": "3", "resultadoB": "0", "visitante": "Burgos"}, {"local": "Zaragoza", "resultadoA": "0", "resultadoB": "1", "visitante": "Mirand\u00e9s"}, {"local": "Huesca", "resultadoA": "0", "resultadoB": "1", "visitante": "Sporting"}, {"local": "Espanyol", "resultadoA": "3", "resultadoB": "0", "visitante": "Racing Ferrol"}]}, {"id": "8e828e6e-1e19-40c2-aa3e-50f1bb6846a0", "nombre": "Jornada 9", "partidos": [{"local": "Alcorc\u00f3n", "resultadoA": "1", "resultadoB": "2", "visitante": "Albacete"}, {"local": "Levante", "resultadoA": "1", "resultadoB": "1", "visitante": "Villarreal B"}, {"local": "Tenerife", "resultadoA": "2", "resultadoB": "0", "visitante": "Racing"}, {"local": "Eldense", "resultadoA": "0", "resultadoB": "1", "visitante": "Real Valladolid"}, {"local": "Oviedo", "resultadoA": "1", "resultadoB": "0", "visitante": "Huesca"}, {"local": "Burgos", "resultadoA": "1", "resultadoB": "0", "visitante": "Legan\u00e9s"}, {"local": "Sporting", "resultadoA": "2", "resultadoB": "0", "visitante": "Elche"}, {"local": "Andorra", "resultadoA": "0", "resultadoB": "1", "visitante": "Zaragoza"}, {"local": "Mirand\u00e9s", "resultadoA": "1", "resultadoB": "3", "visitante": "Eibar"}, {"local": "Cartagena", "resultadoA": "0", "resultadoB": "2", "visitante": "Espanyol"}, {"local": "Racing Ferrol", "resultadoA": "1", "resultadoB": "0", "visitante": "Amorebieta"}]}, {"id": "26b23522-37ab-4c92-98ea-bbeb015f275c", "nombre": "Jornada 10", "partidos": [{"local": "Albacete", "resultadoA": "0", "resultadoB": "2", "visitante": "Levante"}, {"local": "Huesca", "resultadoA": "0", "resultadoB": "1", "visitante": "Eldense"}, {"local": "Racing", "resultadoA": "3", "resultadoB": "2", "visitante": "Sporting"}, {"local": "Legan\u00e9s", "resultadoA": "0", "resultadoB": "0", "visitante": "Oviedo"}, {"local": "Amorebieta", "resultadoA": "1", "resultadoB": "2", "visitante": "Eibar"}, {"local": "Real Valladolid", "resultadoA": "3", "resultadoB": "2", "visitante": "Mirand\u00e9s"}, {"local": "Racing Ferrol", "resultadoA": "1", "resultadoB": "1", "visitante": "Cartagena"}, {"local": "Tenerife", "resultadoA": "2", "resultadoB": "1", "visitante": "Burgos"}, {"local": "Zaragoza", "resultadoA": "0", "resultadoB": "2", "visitante": "Alcorc\u00f3n"}, {"local": "Elche", "resultadoA": "2", "resultadoB": "1", "visitante": "Andorra"}, {"local": "Villarreal B", "resultadoA": "3", "resultadoB": "1", "visitante": "Espanyol"}]}, {"id": "61d80dbb-3fdb-4382-8046-33329f653878", "nombre": "Jornada 11", "partidos": [{"local": "Oviedo", "resultadoA": "3", "resultadoB": "0", "visitante": "Albacete"}, {"local": "Mirand\u00e9s", "resultadoA": "1", "resultadoB": "1", "visitante": "Tenerife"}, {"local": "Cartagena", "resultadoA": "2", "resultadoB": "3", "visitante": "Racing"}, {"local": "Sporting", "resultadoA": "2", "resultadoB": "2", "visitante": "Zaragoza"}, {"local": "Espanyol", "resultadoA": "2", "resultadoB": "0", "visitante": "Real Valladolid"}, {"local": "Burgos", "resultadoA": "3", "resultadoB": "2", "visitante": "Villarreal B"}, {"local": "Eldense", "resultadoA": "1", "resultadoB": "1", "visitante": "Elche"}, {"local": "Andorra", "resultadoA": "2", "resultadoB": "0", "visitante": "Alcorc\u00f3n"}, {"local": "Eibar", "resultadoA": "1", "resultadoB": "1", "visitante": "Huesca"}, {"local": "Legan\u00e9s", "resultadoA": "6", "resultadoB": "0", "visitante": "Amorebieta"}, {"local": "Levante", "resultadoA": "1", "resultadoB": "0", "visitante": "Racing Ferrol"}]}, {"id": "0b75aabe-a060-488d-85fe-8da270a5aa13", "nombre": "Jornada 12", "partidos": [{"local": "Espanyol", "resultadoA": "0", "resultadoB": "1", "visitante": "Legan\u00e9s"}, {"local": "Amorebieta", "resultadoA": "0", "resultadoB": "0", "visitante": "Oviedo"}, {"local": "Villarreal B", "resultadoA": "0", "resultadoB": "3", "visitante": "Mirand\u00e9s"}, {"local": "Tenerife", "resultadoA": "0", "resultadoB": "0", "visitante": "Levante"}, {"local": "Zaragoza", "resultadoA": "2", "resultadoB": "3", "visitante": "Eibar"}, {"local": "Racing Ferrol", "resultadoA": "1", "resultadoB": "1", "visitante": "Eldense"}, {"local": "Huesca", "resultadoA": "0", "resultadoB": "1", "visitante": "Elche"}, {"local": "Albacete", "resultadoA": "1", "resultadoB": "3", "visitante": "Sporting"}, {"local": "Racing", "resultadoA": "3", "resultadoB": "0", "visitante": "Burgos"}, {"local": "Real Valladolid", "resultadoA": "2", "resultadoB": "0", "visitante": "Andorra"}, {"local": "Alcorc\u00f3n", "resultadoA": "1", "resultadoB": "1", "visitante": "Cartagena"}]}, {"id": "d1ccf751-035a-4e63-bb4f-9690006f5ed4", "nombre": "Jornada 13", "partidos": [{"local": "Eibar", "resultadoA": "5", "resultadoB": "1", "visitante": "Real Valladolid"}, {"local": "Eldense", "resultadoA": "2", "resultadoB": "0", "visitante": "Amorebieta"}, {"local": "Andorra", "resultadoA": "2", "resultadoB": "0", "visitante": "Levante"}, {"local": "Sporting", "resultadoA": "2", "resultadoB": "0", "visitante": "Espanyol"}, {"local": "Elche", "resultadoA": "2", "resultadoB": "1", "visitante": "Tenerife"}, {"local": "Mirand\u00e9s", "resultadoA": "2", "resultadoB": "1", "visitante": "Cartagena"}, {"local": "Huesca", "resultadoA": "0", "resultadoB": "0", "visitante": "Albacete"}, {"local": "Legan\u00e9s", "resultadoA": "1", "resultadoB": "0", "visitante": "Villarreal B"}, {"local": "Oviedo", "resultadoA": "2", "resultadoB": "0", "visitante": "Alcorc\u00f3n"}, {"local": "Racing", "resultadoA": "1", "resultadoB": "3", "visitante": "Racing Ferrol"}, {"local": "Burgos", "resultadoA": "1", "resultadoB": "1", "visitante": "Zaragoza"}]}, {"id": "37830368-5b5a-45b2-906d-aac148d104c3", "nombre": "Jornada 14", "partidos": [{"local": "Espanyol", "resultadoA": "2", "resultadoB": "2", "visitante": "Eibar"}, {"local": "Villarreal B", "resultadoA": "0", "resultadoB": "3", "visitante": "Sporting"}, {"local": "Levante", "resultadoA": "2", "resultadoB": "2", "visitante": "Mirand\u00e9s"}, {"local": "Real Valladolid", "resultadoA": "2", "resultadoB": "0", "visitante": "Tenerife"}, {"local": "Albacete", "resultadoA": "1", "resultadoB": "1", "visitante": "Elche"}, {"local": "Racing Ferrol", "resultadoA": "1", "resultadoB": "0", "visitante": "Andorra"}, {"local": "Amorebieta", "resultadoA": "0", "resultadoB": "1", "visitante": "Huesca"}, {"local": "Alcorc\u00f3n", "resultadoA": "3", "resultadoB": "1", "visitante": "Racing"}, {"local": "Cartagena", "resultadoA": "0", "resultadoB": "3", "visitante": "Legan\u00e9s"}, {"local": "Eldense", "resultadoA": "2", "resultadoB": "0", "visitante": "Burgos"}, {"local": "Zaragoza", "resultadoA": "0", "resultadoB": "0", "visitante": "Oviedo"}]}, {"id": "913c3064-aa95-4b50-8580-6fe3d4307b0f", "nombre": "Jornada 15", "partidos": [{"local": "Legan\u00e9s", "resultadoA": "2", "resultadoB": "1", "visitante": "Levante"}, {"local": "Racing", "resultadoA": "2", "resultadoB": "3", "visitante": "Real Valladolid"}, {"local": "Elche", "resultadoA": "2", "resultadoB": "0", "visitante": "Zaragoza"}, {"local": "Mirand\u00e9s", "resultadoA": "1", "resultadoB": "2", "visitante": "Racing Ferrol"}, {"local": "Sporting", "resultadoA": "1", "resultadoB": "1", "visitante": "Amorebieta"}, {"local": "Burgos", "resultadoA": "4", "resultadoB": "2", "visitante": "Alcorc\u00f3n"}, {"local": "Andorra", "resultadoA": "1", "resultadoB": "3", "visitante": "Eldense"}, {"local": "Huesca", "resultadoA": "1", "resultadoB": "1", "visitante": "Espanyol"}, {"local": "Tenerife", "resultadoA": "0", "resultadoB": "1", "visitante": "Villarreal B"}, {"local": "Eibar", "resultadoA": "1", "resultadoB": "1", "visitante": "Albacete"}, {"local": "Oviedo", "resultadoA": "1", "resultadoB": "1", "visitante": "Cartagena"}]}, {"id": "1e252b27-e090-458e-8249-948581651f02", "nombre": "Jornada 16", "partidos": [{"local": "Real Valladolid", "resultadoA": "1", "resultadoB": "1", "visitante": "Legan\u00e9s"}, {"local": "Alcorc\u00f3n", "resultadoA": "0", "resultadoB": "0", "visitante": "Sporting"}, {"local": "Amorebieta", "resultadoA": "2", "resultadoB": "0", "visitante": "Tenerife"}, {"local": "Zaragoza", "resultadoA": "0", "resultadoB": "2", "visitante": "Huesca"}, {"local": "Espanyol", "resultadoA": "2", "resultadoB": "0", "visitante": "Elche"}, {"local": "Racing Ferrol", "resultadoA": "1", "resultadoB": "1", "visitante": "Burgos"}, {"local": "Eldense", "resultadoA": "2", "resultadoB": "2", "visitante": "Mirand\u00e9s"}, {"local": "Oviedo", "resultadoA": "2", "resultadoB": "1", "visitante": "Eibar"}, {"local": "Cartagena", "resultadoA": "1", "resultadoB": "1", "visitante": "Albacete"}, {"local": "Villarreal B", "resultadoA": "0", "resultadoB": "0", "visitante": "Andorra"}, {"local": "Levante", "resultadoA": "2", "resultadoB": "4", "visitante": "Racing"}]}, {"id": "f716bbf8-0e2f-45ff-81ed-d2dd752617fe", "nombre": "Jornada 17", "partidos": [{"local": "Huesca", "resultadoA": "0", "resultadoB": "1", "visitante": "Real Valladolid"}, {"local": "Burgos", "resultadoA": "0", "resultadoB": "0", "visitante": "Andorra"}, {"local": "Racing", "resultadoA": "2", "resultadoB": "0", "visitante": "Villarreal B"}, {"local": "Albacete", "resultadoA": "1", "resultadoB": "0", "visitante": "Zaragoza"}, {"local": "Eibar", "resultadoA": "3", "resultadoB": "1", "visitante": "Levante"}, {"local": "Legan\u00e9s", "resultadoA": "2", "resultadoB": "2", "visitante": "Racing Ferrol"}, {"local": "Elche", "resultadoA": "2", "resultadoB": "0", "visitante": "Amorebieta"}, {"local": "Mirand\u00e9s", "resultadoA": "2", "resultadoB": "1", "visitante": "Oviedo"}, {"local": "Tenerife", "resultadoA": "1", "resultadoB": "1", "visitante": "Cartagena"}, {"local": "Espanyol", "resultadoA": "2", "resultadoB": "0", "visitante": "Alcorc\u00f3n"}, {"local": "Sporting", "resultadoA": "2", "resultadoB": "0", "visitante": "Eldense"}]}, {"id": "ade1d61b-bbd2-4a09-9315-c293b8d1ba03", "nombre": "Jornada 18", "partidos": [{"local": "Oviedo", "resultadoA": "2", "resultadoB": "0", "visitante": "Espanyol"}, {"local": "Eldense", "resultadoA": "0", "resultadoB": "3", "visitante": "Tenerife"}, {"local": "Cartagena", "resultadoA": "1", "resultadoB": "0", "visitante": "Sporting"}, {"local": "Zaragoza", "resultadoA": "1", "resultadoB": "0", "visitante": "Legan\u00e9s"}, {"local": "Levante", "resultadoA": "2", "resultadoB": "1", "visitante": "Real Valladolid"}, {"local": "Andorra", "resultadoA": "1", "resultadoB": "0", "visitante": "Huesca"}, {"local": "Alcorc\u00f3n", "resultadoA": "0", "resultadoB": "2", "visitante": "Elche"}, {"local": "Mirand\u00e9s", "resultadoA": "0", "resultadoB": "0", "visitante": "Racing"}, {"local": "Racing Ferrol", "resultadoA": "5", "resultadoB": "4", "visitante": "Albacete"}, {"local": "Amorebieta", "resultadoA": "0", "resultadoB": "1", "visitante": "Burgos"}, {"local": "Villarreal B", "resultadoA": "1", "resultadoB": "0", "visitante": "Eibar"}]}, {"id": "6b697565-a3ec-4cd9-85ba-468cd1a49c18", "nombre": "Jornada 19", "partidos": [{"local": "Albacete", "resultadoA": "2", "resultadoB": "0", "visitante": "Villarreal B"}, {"local": "Burgos", "resultadoA": "0", "resultadoB": "0", "visitante": "Mirand\u00e9s"}, {"local": "Eibar", "resultadoA": "2", "resultadoB": "2", "visitante": "Andorra"}, {"local": "Elche", "resultadoA": "1", "resultadoB": "2", "visitante": "Cartagena"}, {"local": "Espanyol", "resultadoA": "1", "resultadoB": "1", "visitante": "Zaragoza"}, {"local": "Huesca", "resultadoA": "1", "resultadoB": "0", "visitante": "Racing Ferrol"}, {"local": "Legan\u00e9s", "resultadoA": "1", "resultadoB": "1", "visitante": "Eldense"}, {"local": "Racing", "resultadoA": "2", "resultadoB": "2", "visitante": "Oviedo"}, {"local": "Real Valladolid", "resultadoA": "2", "resultadoB": "1", "visitante": "Amorebieta"}, {"local": "Sporting", "resultadoA": "0", "resultadoB": "0", "visitante": "Levante"}, {"local": "Tenerife", "resultadoA": "1", "resultadoB": "0", "visitante": "Alcorc\u00f3n"}]}, {"id": "75e5382d-189e-4fd3-8480-15c254d5fc66", "nombre": "Jornada 20", "partidos": [{"local": "Alcorc\u00f3n", "resultadoA": "1", "resultadoB": "0", "visitante": "Eibar"}, {"local": "Amorebieta", "resultadoA": "1", "resultadoB": "1", "visitante": "Zaragoza"}, {"local": "Eldense", "resultadoA": "3", "resultadoB": "3", "visitante": "Racing"}, {"local": "Andorra", "resultadoA": "1", "resultadoB": "1", "visitante": "Espanyol"}, {"local": "Cartagena", "resultadoA": "0", "resultadoB": "3", "visitante": "Burgos"}, {"local": "Levante", "resultadoA": "2", "resultadoB": "1", "visitante": "Huesca"}, {"local": "Mirand\u00e9s", "resultadoA": "2", "resultadoB": "0", "visitante": "Albacete"}, {"local": "Racing Ferrol", "resultadoA": "3", "resultadoB": "1", "visitante": "Tenerife"}, {"local": "Oviedo", "resultadoA": "3", "resultadoB": "2", "visitante": "Elche"}, {"local": "Sporting", "resultadoA": "1", "resultadoB": "1", "visitante": "Legan\u00e9s"}, {"local": "Villarreal B", "resultadoA": "1", "resultadoB": "0", "visitante": "Real Valladolid"}]}, {"id": "fb4524bb-43e3-4ddf-a90c-47628c21a4b7", "nombre": "Jornada 21", "partidos": [{"local": "Albacete", "resultadoA": "1", "resultadoB": "1", "visitante": "Eldense"}, {"local": "Amorebieta", "resultadoA": "1", "resultadoB": "2", "visitante": "Alcorc\u00f3n"}, {"local": "Eibar", "resultadoA": "1", "resultadoB": "1", "visitante": "Sporting"}, {"local": "Elche", "resultadoA": "0", "resultadoB": "0", "visitante": "Mirand\u00e9s"}, {"local": "Espanyol", "resultadoA": "3", "resultadoB": "3", "visitante": "Burgos"}, {"local": "Huesca", "resultadoA": "3", "resultadoB": "0", "visitante": "Cartagena"}, {"local": "Legan\u00e9s", "resultadoA": "1", "resultadoB": "1", "visitante": "Tenerife"}, {"local": "Racing", "resultadoA": "2", "resultadoB": "0", "visitante": "Andorra"}, {"local": "Real Valladolid", "resultadoA": "0", "resultadoB": "1", "visitante": "Racing Ferrol"}, {"local": "Zaragoza", "resultadoA": "2", "resultadoB": "2", "visitante": "Levante"}, {"local": "Villarreal B", "resultadoA": "1", "resultadoB": "1", "visitante": "Oviedo"}]}, {"id": "14b61d5f-e123-416c-a779-7412097c719c", "nombre": "Jornada 22", "partidos": [{"local": "", "resultadoA": "", "resultadoB": "", "visitante": ""}, {"local": "", "resultadoA": "", "resultadoB": "", "visitante": ""}, {"local": "", "resultadoA": "", "resultadoB": "", "visitante": ""}, {"local": "", "resultadoA": "", "resultadoB": "", "visitante": ""}, {"local": "", "resultadoA": "", "resultadoB": "", "visitante": ""}, {"local": "", "resultadoA": "", "resultadoB": "", "visitante": ""}, {"local": "", "resultadoA": "", "resultadoB": "", "visitante": ""}, {"local": "", "resultadoA": "", "resultadoB": "", "visitante": ""}, {"local": "", "resultadoA": "", "resultadoB": "", "visitante": ""}, {"local": "", "resultadoA": "", "resultadoB": "", "visitante": ""}, {"local": "", "resultadoA": "", "resultadoB": "", "visitante": ""}]}, {"id": "e353e6be-483a-44d2-8227-9b80fc5d092d", "nombre": "Jornada 23", "partidos": [{"local": "", "resultadoA": "", "resultadoB": "", "visitante": ""}, {"local": "", "resultadoA": "", "resultadoB": "", "visitante": ""}, {"local": "", "resultadoA": "", "resultadoB": "", "visitante": ""}, {"local": "", "resultadoA": "", "resultadoB": "", "visitante": ""}, {"local": "", "resultadoA": "", "resultadoB": "", "visitante": ""}, {"local": "", "resultadoA": "", "resultadoB": "", "visitante": ""}, {"local": "", "resultadoA": "", "resultadoB": "", "visitante": ""}, {"local": "", "resultadoA": "", "resultadoB": "", "visitante": ""}, {"local": "", "resultadoA": "", "resultadoB": "", "visitante": ""}, {"local": "", "resultadoA": "", "resultadoB": "", "visitante": ""}, {"local": "", "resultadoA": "", "resultadoB": "", "visitante": ""}]}, {"id": "58244bd9-19e0-4cd3-9428-9387cc19391b", "nombre": "Jornada 24", "partidos": [{"local": "", "resultadoA": "", "resultadoB": "", "visitante": ""}, {"local": "", "resultadoA": "", "resultadoB": "", "visitante": ""}, {"local": "", "resultadoA": "", "resultadoB": "", "visitante": ""}, {"local": "", "resultadoA": "", "resultadoB": "", "visitante": ""}, {"local": "", "resultadoA": "", "resultadoB": "", "visitante": ""}, {"local": "", "resultadoA": "", "resultadoB": "", "visitante": ""}, {"local": "", "resultadoA": "", "resultadoB": "", "visitante": ""}, {"local": "", "resultadoA": "", "resultadoB": "", "visitante": ""}, {"local": "", "resultadoA": "", "resultadoB": "", "visitante": ""}, {"local": "", "resultadoA": "", "resultadoB": "", "visitante": ""}, {"local": "", "resultadoA": "", "resultadoB": "", "visitante": ""}]}, {"id": "cd0c3396-bbe1-4cd7-a42d-e771179f2af6", "nombre": "Jornada 25", "partidos": [{"local": "", "resultadoA": "", "resultadoB": "", "visitante": ""}, {"local": "", "resultadoA": "", "resultadoB": "", "visitante": ""}, {"local": "", "resultadoA": "", "resultadoB": "", "visitante": ""}, {"local": "", "resultadoA": "", "resultadoB": "", "visitante": ""}, {"local": "", "resultadoA": "", "resultadoB": "", "visitante": ""}, {"local": "", "resultadoA": "", "resultadoB": "", "visitante": ""}, {"local": "", "resultadoA": "", "resultadoB": "", "visitante": ""}, {"local": "", "resultadoA": "", "resultadoB": "", "visitante": ""}, {"local": "", "resultadoA": "", "resultadoB": "", "visitante": ""}, {"local": "", "resultadoA": "", "resultadoB": "", "visitante": ""}, {"local": "", "resultadoA": "", "resultadoB": "", "visitante": ""}]}, {"id": "3e7dca26-eec4-4719-bd8a-8958a72298f5", "nombre": "Jornada 26", "partidos": [{"local": "", "resultadoA": "", "resultadoB": "", "visitante": ""}, {"local": "", "resultadoA": "", "resultadoB": "", "visitante": ""}, {"local": "", "resultadoA": "", "resultadoB": "", "visitante": ""}, {"local": "", "resultadoA": "", "resultadoB": "", "visitante": ""}, {"local": "", "resultadoA": "", "resultadoB": "", "visitante": ""}, {"local": "", "resultadoA": "", "resultadoB": "", "visitante": ""}, {"local": "", "resultadoA": "", "resultadoB": "", "visitante": ""}, {"local": "", "resultadoA": "", "resultadoB": "", "visitante": ""}, {"local": "", "resultadoA": "", "resultadoB": "", "visitante": ""}, {"local": "", "resultadoA": "", "resultadoB": "", "visitante": ""}, {"local": "", "resultadoA": "", "resultadoB": "", "visitante": ""}]}, {"id": "d30249aa-e849-4079-a179-3666666ea896", "nombre": "Jornada 27", "partidos": [{"local": "", "resultadoA": "", "resultadoB": "", "visitante": ""}, {"local": "", "resultadoA": "", "resultadoB": "", "visitante": ""}, {"local": "", "resultadoA": "", "resultadoB": "", "visitante": ""}, {"local": "", "resultadoA": "", "resultadoB": "", "visitante": ""}, {"local": "", "resultadoA": "", "resultadoB": "", "visitante": ""}, {"local": "", "resultadoA": "", "resultadoB": "", "visitante": ""}, {"local": "", "resultadoA": "", "resultadoB": "", "visitante": ""}, {"local": "", "resultadoA": "", "resultadoB": "", "visitante": ""}, {"local": "", "resultadoA": "", "resultadoB": "", "visitante": ""}, {"local": "", "resultadoA": "", "resultadoB": "", "visitante": ""}, {"local": "", "resultadoA": "", "resultadoB": "", "visitante": ""}]}, {"id": "d3d4ced3-4abc-4e68-855d-d309c15fb6f0", "nombre": "Jornada 28", "partidos": [{"local": "", "resultadoA": "", "resultadoB": "", "visitante": ""}, {"local": "", "resultadoA": "", "resultadoB": "", "visitante": ""}, {"local": "", "resultadoA": "", "resultadoB": "", "visitante": ""}, {"local": "", "resultadoA": "", "resultadoB": "", "visitante": ""}, {"local": "", "resultadoA": "", "resultadoB": "", "visitante": ""}, {"local": "", "resultadoA": "", "resultadoB": "", "visitante": ""}, {"local": "", "resultadoA": "", "resultadoB": "", "visitante": ""}, {"local": "", "resultadoA": "", "resultadoB": "", "visitante": ""}, {"local": "", "resultadoA": "", "resultadoB": "", "visitante": ""}, {"local": "", "resultadoA": "", "resultadoB": "", "visitante": ""}, {"local": "", "resultadoA": "", "resultadoB": "", "visitante": ""}]}, {"id": "afce60fd-b930-4e2e-8673-98099b6fbfff", "nombre": "Jornada 29", "partidos": [{"local": "", "resultadoA": "", "resultadoB": "", "visitante": ""}, {"local": "", "resultadoA": "", "resultadoB": "", "visitante": ""}, {"local": "", "resultadoA": "", "resultadoB": "", "visitante": ""}, {"local": "", "resultadoA": "", "resultadoB": "", "visitante": ""}, {"local": "", "resultadoA": "", "resultadoB": "", "visitante": ""}, {"local": "", "resultadoA": "", "resultadoB": "", "visitante": ""}, {"local": "", "resultadoA": "", "resultadoB": "", "visitante": ""}, {"local": "", "resultadoA": "", "resultadoB": "", "visitante": ""}, {"local": "", "resultadoA": "", "resultadoB": "", "visitante": ""}, {"local": "", "resultadoA": "", "resultadoB": "", "visitante": ""}, {"local": "", "resultadoA": "", "resultadoB": "", "visitante": ""}]}, {"id": "af6a9367-2426-41cc-a500-323c4f337330", "nombre": "Jornada 30", "partidos": [{"local": "", "resultadoA": "", "resultadoB": "", "visitante": ""}, {"local": "", "resultadoA": "", "resultadoB": "", "visitante": ""}, {"local": "", "resultadoA": "", "resultadoB": "", "visitante": ""}, {"local": "", "resultadoA": "", "resultadoB": "", "visitante": ""}, {"local": "", "resultadoA": "", "resultadoB": "", "visitante": ""}, {"local": "", "resultadoA": "", "resultadoB": "", "visitante": ""}, {"local": "", "resultadoA": "", "resultadoB": "", "visitante": ""}, {"local": "", "resultadoA": "", "resultadoB": "", "visitante": ""}, {"local": "", "resultadoA": "", "resultadoB": "", "visitante": ""}, {"local": "", "resultadoA": "", "resultadoB": "", "visitante": ""}, {"local": "", "resultadoA": "", "resultadoB": "", "visitante": ""}]}, {"id": "a5df0809-57ec-40b6-8627-a288a8908ea1", "nombre": "Jornada 31", "partidos": [{"local": "", "resultadoA": "", "resultadoB": "", "visitante": ""}, {"local": "", "resultadoA": "", "resultadoB": "", "visitante": ""}, {"local": "", "resultadoA": "", "resultadoB": "", "visitante": ""}, {"local": "", "resultadoA": "", "resultadoB": "", "visitante": ""}, {"local": "", "resultadoA": "", "resultadoB": "", "visitante": ""}, {"local": "", "resultadoA": "", "resultadoB": "", "visitante": ""}, {"local": "", "resultadoA": "", "resultadoB": "", "visitante": ""}, {"local": "", "resultadoA": "", "resultadoB": "", "visitante": ""}, {"local": "", "resultadoA": "", "resultadoB": "", "visitante": ""}, {"local": "", "resultadoA": "", "resultadoB": "", "visitante": ""}, {"local": "", "resultadoA": "", "resultadoB": "", "visitante": ""}]}, {"id": "09af42da-aa4c-451a-b061-5cc4cdc025c7", "nombre": "Jornada 32", "partidos": [{"local": "", "resultadoA": "", "resultadoB": "", "visitante": ""}, {"local": "", "resultadoA": "", "resultadoB": "", "visitante": ""}, {"local": "", "resultadoA": "", "resultadoB": "", "visitante": ""}, {"local": "", "resultadoA": "", "resultadoB": "", "visitante": ""}, {"local": "", "resultadoA": "", "resultadoB": "", "visitante": ""}, {"local": "", "resultadoA": "", "resultadoB": "", "visitante": ""}, {"local": "", "resultadoA": "", "resultadoB": "", "visitante": ""}, {"local": "", "resultadoA": "", "resultadoB": "", "visitante": ""}, {"local": "", "resultadoA": "", "resultadoB": "", "visitante": ""}, {"local": "", "resultadoA": "", "resultadoB": "", "visitante": ""}, {"local": "", "resultadoA": "", "resultadoB": "", "visitante": ""}]}, {"id": "6e498bff-21cf-45e9-8f2b-925903497b7b", "nombre": "Jornada 33", "partidos": [{"local": "", "resultadoA": "", "resultadoB": "", "visitante": ""}, {"local": "", "resultadoA": "", "resultadoB": "", "visitante": ""}, {"local": "", "resultadoA": "", "resultadoB": "", "visitante": ""}, {"local": "", "resultadoA": "", "resultadoB": "", "visitante": ""}, {"local": "", "resultadoA": "", "resultadoB": "", "visitante": ""}, {"local": "", "resultadoA": "", "resultadoB": "", "visitante": ""}, {"local": "", "resultadoA": "", "resultadoB": "", "visitante": ""}, {"local": "", "resultadoA": "", "resultadoB": "", "visitante": ""}, {"local": "", "resultadoA": "", "resultadoB": "", "visitante": ""}, {"local": "", "resultadoA": "", "resultadoB": "", "visitante": ""}, {"local": "", "resultadoA": "", "resultadoB": "", "visitante": ""}]}, {"id": "29a625cf-9f36-4885-aab4-8ebd3a521f42", "nombre": "Jornada 34", "partidos": [{"local": "", "resultadoA": "", "resultadoB": "", "visitante": ""}, {"local": "", "resultadoA": "", "resultadoB": "", "visitante": ""}, {"local": "", "resultadoA": "", "resultadoB": "", "visitante": ""}, {"local": "", "resultadoA": "", "resultadoB": "", "visitante": ""}, {"local": "", "resultadoA": "", "resultadoB": "", "visitante": ""}, {"local": "", "resultadoA": "", "resultadoB": "", "visitante": ""}, {"local": "", "resultadoA": "", "resultadoB": "", "visitante": ""}, {"local": "", "resultadoA": "", "resultadoB": "", "visitante": ""}, {"local": "", "resultadoA": "", "resultadoB": "", "visitante": ""}, {"local": "", "resultadoA": "", "resultadoB": "", "visitante": ""}, {"local": "", "resultadoA": "", "resultadoB": "", "visitante": ""}]}, {"id": "79fab43a-e140-4b06-9131-046945368878", "nombre": "Jornada 35", "partidos": [{"local": "", "resultadoA": "", "resultadoB": "", "visitante": ""}, {"local": "", "resultadoA": "", "resultadoB": "", "visitante": ""}, {"local": "", "resultadoA": "", "resultadoB": "", "visitante": ""}, {"local": "", "resultadoA": "", "resultadoB": "", "visitante": ""}, {"local": "", "resultadoA": "", "resultadoB": "", "visitante": ""}, {"local": "", "resultadoA": "", "resultadoB": "", "visitante": ""}, {"local": "", "resultadoA": "", "resultadoB": "", "visitante": ""}, {"local": "", "resultadoA": "", "resultadoB": "", "visitante": ""}, {"local": "", "resultadoA": "", "resultadoB": "", "visitante": ""}, {"local": "", "resultadoA": "", "resultadoB": "", "visitante": ""}, {"local": "", "resultadoA": "", "resultadoB": "", "visitante": ""}]}, {"id": "cd3516cf-60f6-480f-9829-3ae0b742573a", "nombre": "Jornada 36", "partidos": [{"local": "", "resultadoA": "", "resultadoB": "", "visitante": ""}, {"local": "", "resultadoA": "", "resultadoB": "", "visitante": ""}, {"local": "", "resultadoA": "", "resultadoB": "", "visitante": ""}, {"local": "", "resultadoA": "", "resultadoB": "", "visitante": ""}, {"local": "", "resultadoA": "", "resultadoB": "", "visitante": ""}, {"local": "", "resultadoA": "", "resultadoB": "", "visitante": ""}, {"local": "", "resultadoA": "", "resultadoB": "", "visitante": ""}, {"local": "", "resultadoA": "", "resultadoB": "", "visitante": ""}, {"local": "", "resultadoA": "", "resultadoB": "", "visitante": ""}, {"local": "", "resultadoA": "", "resultadoB": "", "visitante": ""}, {"local": "", "resultadoA": "", "resultadoB": "", "visitante": ""}]}, {"id": "e2a9e89a-7695-4c29-81e5-3e3b4608597b", "nombre": "Jornada 37", "partidos": [{"local": "", "resultadoA": "", "resultadoB": "", "visitante": ""}, {"local": "", "resultadoA": "", "resultadoB": "", "visitante": ""}, {"local": "", "resultadoA": "", "resultadoB": "", "visitante": ""}, {"local": "", "resultadoA": "", "resultadoB": "", "visitante": ""}, {"local": "", "resultadoA": "", "resultadoB": "", "visitante": ""}, {"local": "", "resultadoA": "", "resultadoB": "", "visitante": ""}, {"local": "", "resultadoA": "", "resultadoB": "", "visitante": ""}, {"local": "", "resultadoA": "", "resultadoB": "", "visitante": ""}, {"local": "", "resultadoA": "", "resultadoB": "", "visitante": ""}, {"local": "", "resultadoA": "", "resultadoB": "", "visitante": ""}, {"local": "", "resultadoA": "", "resultadoB": "", "visitante": ""}]}, {"id": "f2cb0a76-5993-4d5d-97ef-8e85b2bcaf71", "nombre": "Jornada 38", "partidos": [{"local": "", "resultadoA": "", "resultadoB": "", "visitante": ""}, {"local": "", "resultadoA": "", "resultadoB": "", "visitante": ""}, {"local": "", "resultadoA": "", "resultadoB": "", "visitante": ""}, {"local": "", "resultadoA": "", "resultadoB": "", "visitante": ""}, {"local": "", "resultadoA": "", "resultadoB": "", "visitante": ""}, {"local": "", "resultadoA": "", "resultadoB": "", "visitante": ""}, {"local": "", "resultadoA": "", "resultadoB": "", "visitante": ""}, {"local": "", "resultadoA": "", "resultadoB": "", "visitante": ""}, {"local": "", "resultadoA": "", "resultadoB": "", "visitante": ""}, {"local": "", "resultadoA": "", "resultadoB": "", "visitante": ""}, {"local": "", "resultadoA": "", "resultadoB": "", "visitante": ""}]}, {"id": "c7f4109c-f99e-4ca4-8d53-ef6cbba5853a", "nombre": "Jornada 39", "partidos": [{"local": "", "resultadoA": "", "resultadoB": "", "visitante": ""}, {"local": "", "resultadoA": "", "resultadoB": "", "visitante": ""}, {"local": "", "resultadoA": "", "resultadoB": "", "visitante": ""}, {"local": "", "resultadoA": "", "resultadoB": "", "visitante": ""}, {"local": "", "resultadoA": "", "resultadoB": "", "visitante": ""}, {"local": "", "resultadoA": "", "resultadoB": "", "visitante": ""}, {"local": "", "resultadoA": "", "resultadoB": "", "visitante": ""}, {"local": "", "resultadoA": "", "resultadoB": "", "visitante": ""}, {"local": "", "resultadoA": "", "resultadoB": "", "visitante": ""}, {"local": "", "resultadoA": "", "resultadoB": "", "visitante": ""}, {"local": "", "resultadoA": "", "resultadoB": "", "visitante": ""}]}, {"id": "d5ff6282-de5b-4308-b593-775bfec3b17e", "nombre": "Jornada 40", "partidos": [{"local": "", "resultadoA": "", "resultadoB": "", "visitante": ""}, {"local": "", "resultadoA": "", "resultadoB": "", "visitante": ""}, {"local": "", "resultadoA": "", "resultadoB": "", "visitante": ""}, {"local": "", "resultadoA": "", "resultadoB": "", "visitante": ""}, {"local": "", "resultadoA": "", "resultadoB": "", "visitante": ""}, {"local": "", "resultadoA": "", "resultadoB": "", "visitante": ""}, {"local": "", "resultadoA": "", "resultadoB": "", "visitante": ""}, {"local": "", "resultadoA": "", "resultadoB": "", "visitante": ""}, {"local": "", "resultadoA": "", "resultadoB": "", "visitante": ""}, {"local": "", "resultadoA": "", "resultadoB": "", "visitante": ""}, {"local": "", "resultadoA": "", "resultadoB": "", "visitante": ""}]}, {"id": "d9181093-6e81-4e86-bec4-7aa83a368ecc", "nombre": "Jornada 41", "partidos": [{"local": "", "resultadoA": "", "resultadoB": "", "visitante": ""}, {"local": "", "resultadoA": "", "resultadoB": "", "visitante": ""}, {"local": "", "resultadoA": "", "resultadoB": "", "visitante": ""}, {"local": "", "resultadoA": "", "resultadoB": "", "visitante": ""}, {"local": "", "resultadoA": "", "resultadoB": "", "visitante": ""}, {"local": "", "resultadoA": "", "resultadoB": "", "visitante": ""}, {"local": "", "resultadoA": "", "resultadoB": "", "visitante": ""}, {"local": "", "resultadoA": "", "resultadoB": "", "visitante": ""}, {"local": "", "resultadoA": "", "resultadoB": "", "visitante": ""}, {"local": "", "resultadoA": "", "resultadoB": "", "visitante": ""}, {"local": "", "resultadoA": "", "resultadoB": "", "visitante": ""}]}, {"id": "107e904b-552e-44a1-bf8b-9fd0f7ac1645", "nombre": "Jornada 42", "partidos": [{"local": "", "resultadoA": "", "resultadoB": "", "visitante": ""}, {"local": "", "resultadoA": "", "resultadoB": "", "visitante": ""}, {"local": "", "resultadoA": "", "resultadoB": "", "visitante": ""}, {"local": "", "resultadoA": "", "resultadoB": "", "visitante": ""}, {"local": "", "resultadoA": "", "resultadoB": "", "visitante": ""}, {"local": "", "resultadoA": "", "resultadoB": "", "visitante": ""}, {"local": "", "resultadoA": "", "resultadoB": "", "visitante": ""}, {"local": "", "resultadoA": "", "resultadoB": "", "visitante": ""}, {"local": "", "resultadoA": "", "resultadoB": "", "visitante": ""}, {"local": "", "resultadoA": "", "resultadoB": "", "visitante": ""}, {"local": "", "resultadoA": "", "resultadoB": "", "visitante": ""}]}]